FPGA/Coop/ctrl4_xdig/hdl/tb/emc_master.v
//------------------------------------------------------------------------------
// (C) Copyright 2013, NXP Semiconductors
//     All rights reserved.
//
// PROPRIETARY INFORMATION
//
// The information contained in this file is the property of NXP Semiconductors.
// Except as specifically authorized in writing by NXP, the holder of this
// file: (1) shall keep all information contained herein confidential and
// shall protect same in whole or in part from disclosure and dissemination to
// all third parties and (2) shall use same for operation and maintenance
// purposes only.
// -----------------------------------------------------------------------------
// File name:		emc_master.v
// Project:		Ctrl4 extended digital, timing generator image
// Purpose:		LPC43xx EMC master behavorial model for testbench
// Author: 		Roger Williams <roger.williams@nxp.com> (RAW)
// -----------------------------------------------------------------------------
// Supported cycles:	Master Read/Write
// Data port:		8, 16, 32-bit; 8-bit granularity
// Data ordering:	little endian
// Parameters:		AW = width of address bus (default 8)
// -----------------------------------------------------------------------------
// 0.10.0  2013-09-30 (RAW) Initial entry
//------------------------------------------------------------------------------

`include "timescale.v"

module emc_master (clk_i, rst_i, A, D, BLSN, CSN, WEN, OEN);
   parameter AW = 8, WAITOEN = 0, WAITRD = 0, WAITWEN = 0, WAITWR = 0;
   input wire		clk_i;	// internal 200MHz clock
   input wire		rst_i;	// internal reset
   output reg [AW-1:0] 	A = {AW{1'bx}};
   inout wire [15:0] 	D;
   output reg [3:0] 	BLSN = 4'b1111;
   output reg		CSN = 1'b1;
   output reg		WEN = 1'b1;
   output reg		OEN = 1'b1;
   
   reg [15:0] 		dat_o = 0;
   reg [15:0] 		data_rd = 0;
   reg [15:0] 		data_rd2 = 0;
   reg [3:0] 		waito1, waito2, waitw1, waitw2;
   reg 			go = 0;
   reg 			stop = 0;
   integer 		address, iswrite;

   assign D = (~CSN & iswrite) ? dat_o : {16{1'bz}};

   // read single
   task rd (input [AW-1:0] adr, output [15:0] result);
      begin
	 iswrite = 0;
	 waito1 <= WAITOEN;
	 waito2 <= WAITRD;
	 @ (posedge clk_i);
	 A = adr[AW-1:0];
	 CSN = 0;
	 while (waito1 != 0)
	   @ (posedge clk_i) waito1 = waito1 - 1;
	 OEN = 0;
	 while (waito2 != 0)
	   @ (posedge clk_i) waito2 = waito2 - 1;
	 data_rd <= D;
	 @ (posedge clk_i);
	 @ (posedge clk_i);
	 @ (posedge clk_i);
	 OEN = 1;
	 CSN = 1;
	 result = data_rd;
      end
   endtask
   
   // write single
   task wr (input [AW-1:0] adr, input [15:0] dat);
      begin
	 iswrite = 1;
	 waitw1 <= WAITWEN;
	 waitw2 <= WAITWR;
	 @ (posedge clk_i);
	 A = adr[AW-1:0];
	 dat_o = dat[15:0];
	 CSN = 0;
	 @ (posedge clk_i);
	 while (waitw1 != 0)
	   @ (posedge clk_i) waitw1 = waitw1 - 1;
	 WEN = 0;
	 @ (posedge clk_i);
	 while (waitw2 != 0)
	   @ (posedge clk_i) waitw2 = waitw2 - 1;
	 WEN = 1;
	 @ (posedge clk_i);
	 CSN = 1;
      end
   endtask // wr

   // write double
   task wr2 (input [AW-1:0] adr, input [31:0] dat);
      begin
	 iswrite = 1;
	 waitw1 <= WAITWEN;
	 waitw2 <= WAITWR;
	 @ (posedge clk_i);
	 A = adr[AW-1:0];
	 dat_o = dat[15:0];
	 CSN = 0;
	 @ (posedge clk_i);
	 while (waitw1 != 0)
	   @ (posedge clk_i) waitw1 = waitw1 - 1;
	 WEN = 0;
	 @ (posedge clk_i);
	 while (waitw2 != 0)
	   @ (posedge clk_i) waitw2 = waitw2 - 1;
	 WEN = 1;
	 A = adr[AW-1:0] + 2;
	 dat_o = dat[31:16];
	 waitw1 <= WAITWEN;
	 waitw2 <= WAITWR;
	 @ (posedge clk_i);
	 while (waitw1 != 0)
	   @ (posedge clk_i) waitw1 = waitw1 - 1;
	 WEN = 0;
	 @ (posedge clk_i);
	 while (waitw2 != 0)
	   @ (posedge clk_i) waitw2 = waitw2 - 1;
	 WEN = 1;
	 @ (posedge clk_i);
	 CSN = 1;
      end
   endtask // wr

endmodule

FPGA/Coop/ctrl4_xdig/hdl/tb/clkrst.v
//------------------------------------------------------------------------------
// (C) Copyright 2013, NXP Semiconductors
//     All rights reserved.
//
// PROPRIETARY INFORMATION
//
// The information contained in this file is the property of NXP Semiconductors.
// Except as specifically authorized in writing by NXP, the holder of this
// file: (1) shall keep all information contained herein confidential and
// shall protect same in whole or in part from disclosure and dissemination to
// all third parties and (2) shall use same for operation and maintenance
// purposes only.
// -----------------------------------------------------------------------------
// File name:		clkrst.v
// Project:		Ctrl4 extended digital, timing generator image
// Purpose:		Testbench clock and reset generator
// Author: 		Roger Williams <roger.williams@nxp.com> (RAW)
// -----------------------------------------------------------------------------
// 0.10.0  2013-09-30 (RAW) Initial entry
//------------------------------------------------------------------------------

`include "timescale.v"

module clkrst (clk, clk2x, rst);

   // I/O ports
   output reg	clk = 0;	// clock
   output reg	clk2x = 0;	// clock
   output reg	rst = 0;	// reset

   task reset;
      begin
	 rst = 1'b0;
	 @ (negedge clk) rst <= 1'b1;
	 @ (negedge clk);
	 @ (negedge clk);
	 @ (negedge clk);
	 @ (negedge clk) rst <= 1'b0;
      end
   endtask // reset
   
   // 100 MHz clock
   always begin
      #5 clk <= 1'b0;
      #5 clk <= 1'b1;
   end

   // 200 MHz clock
   always begin
      #2 clk2x <= 1'b0;
      #3 clk2x <= 1'b1;
   end

endmodule

FPGA/Coop/ctrl4_xdig/hdl/tb/emc_test.v
//------------------------------------------------------------------------------
// (C) Copyright 2013, NXP Semiconductors
//     All rights reserved.
//
// PROPRIETARY INFORMATION
//
// The information contained in this file is the property of NXP Semiconductors.
// Except as specifically authorized in writing by NXP, the holder of this
// file: (1) shall keep all information contained herein confidential and
// shall protect same in whole or in part from disclosure and dissemination to
// all third parties and (2) shall use same for operation and maintenance
// purposes only.
// -----------------------------------------------------------------------------
// File name:		emc_test.v
// Project:		Ctrl4 extended digital, timing generator image
// Purpose:		Verify LPC43xx EMC master behavorial model
// Author: 		Roger Williams <roger.williams@nxp.com> (RAW)
// -----------------------------------------------------------------------------
// 0.10.0  2013-09-30 (RAW) Initial entry
//------------------------------------------------------------------------------

`include "timescale.v"

module emc_test();
   parameter AW = 8, DW = 16, WAITOEN = 0, WAITRD = 0, WAITWEN = 0, WAITWR = 0;
   // interconnect wires
   wire			clk;			// clock
   wire			rst;			// reset
   wire [AW-1:0] 	A;			// address bus
   wire [3:0] 		BLSN;			// byte lane selects
   wire			WEN;			// write enable
   wire			OEN;			// output enable
   wire			CSN;			// cycle select
   wire [DW-1:0] 	D;			// data bus from EMC to DUT

   reg [DW-1:0] 	dat_r;
   reg [31:0] 		result, i;
   integer 		read;

   assign D = read ? dat_r : {DW{1'bz}};

   initial begin
      $dumpfile("emc_test.vcd");
      $dumpvars(0);

      clkrst.reset;
      read = 0;
      @ (posedge clk);
      $write("Testing write...");
      emc.wr(8'ha5, 16'habcd);
      @ (posedge clk);

      $write("read...");
      read = 1;
      dat_r = 16'hba98;
      emc.rd(8'h07, result);
      read = 0;
      @ (posedge clk);
      @ (posedge clk);
      @ (posedge clk);
      $write("done\n");
      
      $finish;
   end

   initial begin
      #1000 $write("ERROR: EMC testbench timed out\n");
      $stop(2);
   end

   // clock/reset generator
   clkrst clkrst(.clk(clk), .rst(rst));

   // master EMC BFM
   emc_master #(.AW(AW),.DW(DW), .WAITOEN(WAITOEN), .WAITRD(WAITRD), .WAITWEN(WAITWEN), .WAITWR(WAITWR))
   emc(.clk_i(clk), .rst_i(rst), .A(A), .D(D), .BLSN(BLSN), .WEN(WEN), .CSN(CSN), .OEN(OEN));
   
endmodule

FPGA/Coop/ctrl4_xdig/hdl/tb/emc_test.vcd
$date
   Fri Nov  8 15:15:34 2013
$end
$version
  P.68d
$end
$timescale
  1ps
$end
$scope module emc_test $end
$var wire 1 I clk $end
$var wire 1 J rst $end
$var wire 1 # A [7] $end
$var wire 1 $ A [6] $end
$var wire 1 % A [5] $end
$var wire 1 & A [4] $end
$var wire 1 ' A [3] $end
$var wire 1 ( A [2] $end
$var wire 1 ) A [1] $end
$var wire 1 * A [0] $end
$var wire 1 + BLSN [3] $end
$var wire 1 , BLSN [2] $end
$var wire 1 - BLSN [1] $end
$var wire 1 . BLSN [0] $end
$var wire 1 / WEN $end
$var wire 1 0 OEN $end
$var wire 1 1 CSN $end
$var wire 1 K D [15] $end
$var wire 1 L D [14] $end
$var wire 1 M D [13] $end
$var wire 1 N D [12] $end
$var wire 1 O D [11] $end
$var wire 1 P D [10] $end
$var wire 1 Q D [9] $end
$var wire 1 R D [8] $end
$var wire 1 S D [7] $end
$var wire 1 T D [6] $end
$var wire 1 U D [5] $end
$var wire 1 V D [4] $end
$var wire 1 W D [3] $end
$var wire 1 X D [2] $end
$var wire 1 Y D [1] $end
$var wire 1 Z D [0] $end
$var reg 16 B dat_r [15:0] $end
$var reg 32 C result [31:0] $end
$var reg 32 D i [31:0] $end
$var integer 32 E read $end
$scope module clkrst $end
$var reg 1 F clk $end
$var reg 1 G clk2x $end
$var reg 1 H rst $end
$scope task reset $end
$upscope $end
$upscope $end
$scope module emc $end
$var wire 1 I clk_i $end
$var wire 1 J rst_i $end
$var wire 1 K D [15] $end
$var wire 1 L D [14] $end
$var wire 1 M D [13] $end
$var wire 1 N D [12] $end
$var wire 1 O D [11] $end
$var wire 1 P D [10] $end
$var wire 1 Q D [9] $end
$var wire 1 R D [8] $end
$var wire 1 S D [7] $end
$var wire 1 T D [6] $end
$var wire 1 U D [5] $end
$var wire 1 V D [4] $end
$var wire 1 W D [3] $end
$var wire 1 X D [2] $end
$var wire 1 Y D [1] $end
$var wire 1 Z D [0] $end
$var reg 8 [ A [7:0] $end
$var reg 4 \ BLSN [3:0] $end
$var reg 1 ] CSN $end
$var reg 1 ^ WEN $end
$var reg 1 _ OEN $end
$var reg 16 ` dat_o [15:0] $end
$var reg 16 a data_rd [15:0] $end
$var reg 16 b data_rd2 [15:0] $end
$var reg 4 c waito1 [3:0] $end
$var reg 4 d waito2 [3:0] $end
$var reg 4 e waitw1 [3:0] $end
$var reg 4 f waitw2 [3:0] $end
$var reg 1 g go $end
$var reg 1 h stop $end
$var integer 32 i address $end
$var integer 32 j iswrite $end
$scope task rd $end
$var reg 8 k adr [7:0] $end
$var reg 16 l result [15:0] $end
$upscope $end
$scope task wr $end
$var reg 8 m adr [7:0] $end
$var reg 16 n dat [15:0] $end
$upscope $end
$scope task wr2 $end
$var reg 8 o adr [7:0] $end
$var reg 32 p dat [31:0] $end
$upscope $end
$upscope $end
$upscope $end
$enddefinitions $end
#0
$dumpvars
0I
0J
x*
x)
x(
x'
x&
x%
x$
x#
1.
1-
1,
1+
1/
10
11
xZ
xY
xX
xW
xV
xU
bx B
bx C
bx D
bx E
xT
xS
xR
xQ
xP
xO
xN
xM
xL
xK
0F
0G
0H
bx [
b1111 \
1]
1^
1_
b0 `
b0 a
b0 b
bx c
bx d
bx e
bx f
0g
0h
bx i
bx j
bx k
bx l
bx m
bx n
bx o
bx p
$end
#5000
1G
#7000
0G
#10000
1I
1F
1G
#12000
0G
#15000
0I
1J
0F
1G
1H
#17000
0G
#20000
1I
1F
1G
#22000
0G
#25000
0I
0F
1G
#27000
0G
#30000
1I
1F
1G
#32000
0G
#35000
0I
0F
1G
#37000
0G
#40000
1I
1F
1G
#42000
0G
#45000
0I
0F
1G
#47000
0G
#50000
1I
1F
1G
#52000
0G
#55000
0I
0J
xZ
xY
xX
xW
xV
xU
b0 E
xT
xS
xR
xQ
xP
xO
xN
xM
xL
xK
0F
1G
0H
#57000
0G
#60000
1I
zZ
zY
zX
zW
zV
zU
zT
zS
zR
zQ
zP
zO
zN
zM
zL
zK
1F
1G
b0 e
b0 f
b1 j
b10100101 m
b1010101111001101 n
#62000
0G
#65000
0I
0F
1G
#67000
0G
#70000
1I
1*
0)
1(
0'
0&
1%
0$
1#
01
1Z
0Y
1X
1W
0V
0U
1T
1S
1R
1Q
0P
1O
0N
1M
0L
1K
1F
1G
b10100101 [
0]
b1010101111001101 `
#72000
0G
#75000
0I
0F
1G
#77000
0G
#80000
1I
0/
1F
1G
0^
#82000
0G
#85000
0I
0F
1G
#87000
0G
#90000
1I
1/
1F
1G
1^
#92000
0G
#95000
0I
0F
1G
#97000
0G
#100000
1I
11
zZ
zY
zX
zW
zV
zU
zT
zS
zR
zQ
zP
zO
zN
zM
zL
zK
1F
1G
1]
#102000
0G
#105000
0I
0F
1G
#107000
0G
#110000
1I
0Z
0Y
0X
1W
1V
0U
b1011101010011000 B
b1 E
0T
1S
0R
1Q
0P
1O
1N
1M
0L
1K
1F
1G
b0 c
b0 d
b0 j
b111 k
#112000
0G
#115000
0I
0F
1G
#117000
0G
#120000
1I
1)
0%
0#
00
01
1F
1G
b111 [
0]
0_
b1011101010011000 a
#122000
0G
#125000
0I
0F
1G
#127000
0G
#130000
1I
1F
1G
#132000
0G
#135000
0I
0F
1G
#137000
0G
#140000
1I
1F
1G
#142000
0G
#145000
0I
0F
1G
#147000
0G
#150000
1I
10
11
zZ
zY
zX
zW
zV
zU
b1011101010011000 C
b0 E
zT
zS
zR
zQ
zP
zO
zN
zM
zL
zK
1F
1G
1]
1_
b1011101010011000 l
